cdef_cohort/__init__.py
cdef_cohort/__main__.py
cdef_cohort/_version.py
cdef_cohort/config.py
cdef_cohort/logging_config.py
cdef_cohort/main.py
cdef_cohort/mapping_utils.py
cdef_cohort/population.py
cdef_cohort/settings.py
cdef_cohort/config/__init__.py
cdef_cohort/config/examples/__init__.py
cdef_cohort/config/examples/standard_config.py
cdef_cohort/events/plotting.py
cdef_cohort/events/summaries.py
cdef_cohort/functions/check_parquet.py
cdef_cohort/functions/population_summary.py
cdef_cohort/functions/table1.py
cdef_cohort/mappings/beskst13.json
cdef_cohort/mappings/civst.json
cdef_cohort/mappings/fm_mark.json
cdef_cohort/mappings/hustype.json
cdef_cohort/mappings/icd10.json
cdef_cohort/mappings/isced.json
cdef_cohort/mappings/jobkat.json
cdef_cohort/mappings/plads.json
cdef_cohort/mappings/pre_socio.json
cdef_cohort/mappings/reg.json
cdef_cohort/mappings/scd.json
cdef_cohort/mappings/socio13.json
cdef_cohort/mappings/statsb.json
cdef_cohort/mappings/tilknyt.json
cdef_cohort/models/analytical_data.py
cdef_cohort/models/config.py
cdef_cohort/registers/__init__.py
cdef_cohort/registers/akm.py
cdef_cohort/registers/base.py
cdef_cohort/registers/bef.py
cdef_cohort/registers/factory.py
cdef_cohort/registers/generic.py
cdef_cohort/registers/idan.py
cdef_cohort/registers/ind.py
cdef_cohort/registers/longitudinal.py
cdef_cohort/registers/lpr3_diagnoser.py
cdef_cohort/registers/lpr3_kontakter.py
cdef_cohort/registers/lpr_adm.py
cdef_cohort/registers/lpr_bes.py
cdef_cohort/registers/lpr_diag.py
cdef_cohort/registers/manager.py
cdef_cohort/registers/registry.py
cdef_cohort/registers/uddf.py
cdef_cohort/schemas/all.py
cdef_cohort/services/__init__.py
cdef_cohort/services/analytical_data_service.py
cdef_cohort/services/base.py
cdef_cohort/services/cohort_service.py
cdef_cohort/services/config_service.py
cdef_cohort/services/container.py
cdef_cohort/services/data_service.py
cdef_cohort/services/event_service.py
cdef_cohort/services/mapping_service.py
cdef_cohort-0.8.0.dist-info/METADATA
cdef_cohort-0.8.0.dist-info/WHEEL
cdef_cohort-0.8.0.dist-info/entry_points.txt
cdef_cohort-0.8.0.dist-info/licenses/LICENSE.txt
cdef_cohort-0.8.0.dist-info/RECORD
