Metadata-Version: 2.3
Name: cdef_cohort
Version: 0.8.0
Summary: Add your description here
Project-URL: Source Code, https://github.com/LGS-Research-Group/cdef-cohort-generation/tree/b2fa85bb206972e2e8e2dc775cfb5cfd1f5b8d56
Author-email: Tobias Kragholm <50784887+tkragholm@users.noreply.github.com>
License-Expression: MIT
License-File: LICENSE.txt
Requires-Python: >=3.12
Requires-Dist: imohash>=1.1.0
Requires-Dist: lifelines>=0.29.0
Requires-Dist: matplotlib>=3.9.2
Requires-Dist: plotly-geo>=1.0.0
Requires-Dist: plotly>=5.24.1
Requires-Dist: polars[all]>=1.9.0
Requires-Dist: pydantic-settings>=2.5.2
Requires-Dist: pydantic[mypy]>=2.9.2
Requires-Dist: rich>=13.9.2
Requires-Dist: seaborn[stats]>=0.13.2
Requires-Dist: tqdm>=4.66.5
